multisite/__init__.py
multisite/__version__.py
multisite/admin.py
multisite/forms.py
multisite/hacks.py
multisite/hosts.py
multisite/managers.py
multisite/middleware.py
multisite/models.py
multisite/template_loader.py
multisite/test_settings.py
multisite/tests.py
multisite/threadlocals.py
multisite/management/__init__.py
multisite/management/commands/__init__.py
multisite/management/commands/update_public_suffix_list.py
multisite/migrations/0001_initial.py
multisite/migrations/__init__.py
multisite/template/__init__.py
multisite/template/loaders/__init__.py
multisite/template/loaders/filesystem.py
multisite/test_templates/example.com/example.html
multisite/test_templates/multisite_templates/test.html
django_multisite-1.9.0.dist-info/METADATA
django_multisite-1.9.0.dist-info/WHEEL
django_multisite-1.9.0.dist-info/top_level.txt
django_multisite-1.9.0.dist-info/RECORD
