Metadata-Version: 2.1
Name: django-multisite
Version: 1.9.0
Summary: Serve multiple sites from a single Django application
Home-page: http://github.com/ecometrica/django-multisite
Author: Leonid S Shestera
Author-email: leonid@shestera.ru
Maintainer: Ecometrica
Maintainer-email: dev@ecometrica.com
License: UNKNOWN
Platform: UNKNOWN
Classifier: Development Status :: 4 - Beta
Classifier: Environment :: Web Environment
Classifier: Framework :: Django
Classifier: Intended Audience :: Developers
Classifier: License :: OSI Approved :: BSD License
Classifier: Operating System :: OS Independent
Classifier: Programming Language :: Python
Classifier: Programming Language :: Python :: 2.7
Classifier: Programming Language :: Python :: 3.4
Classifier: Programming Language :: Python :: 3.5
Classifier: Programming Language :: Python :: 3.6
Classifier: Programming Language :: Python :: 3.7
Classifier: Programming Language :: Python :: 3.8
Classifier: Topic :: Internet
Classifier: Topic :: Internet :: WWW/HTTP
Classifier: Topic :: Software Development :: Libraries
Classifier: Topic :: Utilities
Requires-Dist: pluggy (<1.0,>=0.12)
Requires-Dist: tldextract (<3.0,>=1.2)
